setup.py
caseConverter/__init__.py
caseConverter/case_converter.py
case_convertos.egg-info/PKG-INFO
case_convertos.egg-info/SOURCES.txt
case_convertos.egg-info/dependency_links.txt
case_convertos.egg-info/entry_points.txt
case_convertos.egg-info/top_level.txt