Metadata-Version: 2.1
Name: case-convertos
Version: 0.0.1
Summary: Convert a string to upper case
Author: Mohamed Moumni
